browserchief/__init__.py
browserchief/main.py
browserchief-0.1.0.dist-info/licenses/LICENSE
browserchief-0.1.0.dist-info/METADATA
browserchief-0.1.0.dist-info/WHEEL
browserchief-0.1.0.dist-info/top_level.txt
browserchief-0.1.0.dist-info/RECORD
