Metadata-Version: 2.4
Name: browserchief
Version: 0.1.0
Summary: browserchief
Author-email: Anatolii Maliarov <anatolii.maliarov@railam.com>
Project-URL: Homepage, https://github.com/railam-llc/browserchief
Project-URL: Documentation, https://github.com/railam-llc/browserchief
Project-URL: Issues, https://github.com/railam-llc/browserchief/issues
Requires-Python: >=3.10
License-File: LICENSE
Dynamic: license-file
